avoca/__init__.py
avoca/export_nas.py
avoca/flagging.py
avoca/flags.py
avoca/io.py
avoca/logging.py
avoca/manager.py
avoca/requirements.py
avoca/settings.py
avoca/bindings/__init__.py
avoca/bindings/ebas.py
avoca/bindings/ebas_flags.py
avoca/bindings/gcwerks-report.conf
avoca/bindings/gcwerks.py
avoca/bindings/gcwerks_gui.py
avoca/bindings/nabel.py
avoca/bindings/qa_tool.py
avoca/bindings/synspec.py
avoca/qa_class/__init__.py
avoca/qa_class/abstract.py
avoca/qa_class/concs.py
avoca/qa_class/generate_classes_doc.py
avoca/qa_class/invalid.py
avoca/qa_class/rt.py
avoca/qa_class/test.py
avoca/qa_class/zscore.py
avoca/testing/__init__.py
avoca/testing/df.py
avoca/utils/__init__.py
avoca/utils/flags_doc.py
avoca/utils/torch_models.py
avoca-0.11.4.dist-info/METADATA
avoca-0.11.4.dist-info/WHEEL
avoca-0.11.4.dist-info/licenses/LICENCE.txt
avoca-0.11.4.dist-info/RECORD
