Metadata-Version: 2.4
Name: avoca
Version: 0.11.4
Summary: @voc@: Quality assessement of measurement data
Project-URL: Homepage, https://gitlab.com/empa503/atmospheric-measurements/avoca
Project-URL: Bug Tracker, https://gitlab.com/empa503/atmospheric-measurements/avoca/-/issues
Project-URL: Documentation, http://avoca.readthedocs.io/
Author-email: Lionel Constantin <lionel.constantin@empa.ch>
License-File: LICENCE.txt
Classifier: License :: OSI Approved :: MIT License
Classifier: Operating System :: OS Independent
Classifier: Programming Language :: Python :: 3
Requires-Python: >=3.8
Requires-Dist: pandas
Requires-Dist: pydantic
Requires-Dist: pyyaml
Provides-Extra: dev
Requires-Dist: black; extra == 'dev'
Requires-Dist: flake8; extra == 'dev'
Requires-Dist: isort; extra == 'dev'
Requires-Dist: mypy; extra == 'dev'
Requires-Dist: pylint; extra == 'dev'
Requires-Dist: pytest; extra == 'dev'
Provides-Extra: doc
Requires-Dist: ebas-io; extra == 'doc'
Requires-Dist: furo; extra == 'doc'
Requires-Dist: matplotlib; extra == 'doc'
Requires-Dist: myst-nb; extra == 'doc'
Requires-Dist: myst-parser; extra == 'doc'
Requires-Dist: sphinx; extra == 'doc'
